{
  "slug": "ofca",
  "url": "https://www.ofca.gov.hk/en/home/",
  "picked": {
    "href": "https://www.ofca.gov.hk/favicon.ico",
    "ext": "ico",
    "mime": "image/x-icon",
    "bytes": 1150,
    "file": "ofca.ico"
  },
  "candidates": [
    {
      "source": "default",
      "rel": "icon",
      "href": "https://www.ofca.gov.hk/favicon.ico",
      "ok": true,
      "ext": "ico",
      "mime": "image/x-icon",
      "bytes": 1150,
      "file": "raw/icon-0.ico",
      "error": null
    }
  ]
}